{
  "cacheVersion": 2,
  "canonicalLink": "https://openlibrary.org/works/OL19666878W",
  "coverHash": "5b2907ac265a32831a60640accf5c77f9ab57ccf8ce45ce0728432765647fcae",
  "coverSourceMime": "image/jpeg",
  "coverSourceUrl": "https://ia600507.us.archive.org/view_archive.php?archive=%2F8%2Fitems%2Fl_covers_0009%2Fl_covers_0009_46.zip&file=0009466557-L.jpg",
  "entityId": "openlibrary:/works/OL19666878W",
  "expiryDate": null,
  "height": 500,
  "isbn": "",
  "resolvedAuthor": "Moisés Naím",
  "resolvedTitle": "The end of power",
  "score": 1.0,
  "source": "openlibrary",
  "sourcePublishedAt": "",
  "title": "The end of power",
  "titleNormalized": "the end of power",
  "type": "book",
  "verifiedAt": "2026-07-18T10:21:41.314455Z",
  "width": 322
}