{
  "cacheVersion": 2,
  "canonicalLink": "https://observador.pt/opiniao/da-fragmentacao-a-federacao-ii/",
  "coverHash": "24b0cdcadb220477b8ff820c7cc6d561725efcbce0920758795d4a734c0ca099",
  "coverSourceMime": "image/jpeg",
  "coverSourceUrl": "https://wm.observador.pt/wm-op/wide-circle/https%3A%2F%2Fbordalo.observador.pt%2Fv2%2Frs%3Afill%3A303%3A303%2Fc%3A1128%3A1128%3Anowe%3A413%3A200%2Fq%3A100%2Ff%3Apng%2Fplain%2Fhttps%3A%2F%2Fs3.observador.pt%2Fwp-content%2Fuploads%2F2021%2F02%2F09212710%2Fvfs-2020.jpeg",
  "entityId": "article:url:1e4660e0df789045d7eb2103",
  "expiryDate": "2026-08-17T23:15:57Z",
  "height": 630,
  "isbn": "",
  "resolvedAuthor": "observador.pt",
  "resolvedTitle": "Da Fragmentação à Federação (II)",
  "score": 1.0,
  "source": "news-rss:observador.pt",
  "sourcePublishedAt": "2026-07-18T23:15:57Z",
  "title": "Da Fragmentação à Federação (II)",
  "titleNormalized": "da fragmentacao a federacao ii",
  "type": "highlight",
  "verifiedAt": "2026-07-18T23:33:02.353092Z",
  "width": 1200
}