{
  "cacheVersion": 2,
  "canonicalLink": "https://www.imdb.com/title/tt0056218/",
  "coverHash": "6efb73840732b5ec9c33172e7ecca062d8e48925fb8ea6b19e3f51fa874f1d79",
  "coverSourceMime": "image/jpeg",
  "coverSourceUrl": "https://upload.wikimedia.org/wikipedia/commons/thumb/7/70/Sinatra_and_Harvey_in_Manchurian_Candidate_NYWTS.tiff/lossy-page1-1280px-Sinatra_and_Harvey_in_Manchurian_Candidate_NYWTS.tiff.jpg",
  "entityId": "imdb:tt0056218",
  "expiryDate": null,
  "height": 1613,
  "isbn": "",
  "resolvedAuthor": "John Frankenheimer",
  "resolvedTitle": "The Manchurian Candidate",
  "score": 1.0,
  "source": "wikidata+imdb",
  "sourcePublishedAt": "",
  "title": "The Manchurian Candidate",
  "titleNormalized": "the manchurian candidate",
  "type": "movie",
  "verifiedAt": "2026-07-18T10:21:04.967482Z",
  "width": 1280
}